Metadata-Version: 2.1
Name: django-postgres-reindex-command
Version: 2020.7.1
Summary: reindex postgres indexes using django command
Home-page: https://github.com/andrewp-as-is/django-postgres-reindex-command.py
License: Unlicense
Keywords: Django postgres reindex
Platform: UNKNOWN
Classifier: Framework :: Django
Classifier: License :: Public Domain
Classifier: Operating System :: OS Independent
Classifier: Programming Language :: Python :: 3
